setup.cfg
setup.py
dogfactory/__init__.py
dogfactory/makedog.py
dogfactory.egg-info/PKG-INFO
dogfactory.egg-info/SOURCES.txt
dogfactory.egg-info/dependency_links.txt
dogfactory.egg-info/entry_points.txt
dogfactory.egg-info/top_level.txt