Metadata-Version: 1.0
Name: dogfactory
Version: 1.0
Summary: A factory that makes dogs! (The best kind of factory.)
Home-page: https://github.com/chelseadole/dogfactory
Author: Chelsea Dole
Author-email: chelseadole@gmail.com
License: UNKNOWN
Keywords: dogs,factory,woof
Platform: UNKNOWN
